sqwalk/__init__.py
sqwalk/objects.py
sqwalk/utils.py
sqwalk-0.5.3.dist-info/LICENSE
sqwalk-0.5.3.dist-info/METADATA
sqwalk-0.5.3.dist-info/WHEEL
sqwalk-0.5.3.dist-info/top_level.txt
sqwalk-0.5.3.dist-info/RECORD
