Metadata-Version: 2.1
Name: sqwalk
Version: 0.5.3
Summary: A simple quantum walk simulator in python
Home-page: https://github.com/Buffoni/SQWalk
Author: Lorenzo Buffoni
License: Apache License 2.0
Keywords: quantum walker stochastic decomposition
Platform: UNKNOWN
License-File: LICENSE
Requires-Dist: qutip
Requires-Dist: numpy
Requires-Dist: matplotlib
Requires-Dist: qiskit
